cace/__init__.py
cace/__main__.py
cace/__version__.py
cace/cace_cli.py
cace/cace_gui.py
cace/open_pdks_rev
cace/common/__init__.py
cace/common/cace_read.py
cace/common/cace_regenerate.py
cace/common/cace_write.py
cace/common/common.py
cace/common/custom_semaphore.py
cace/common/misc.py
cace/common/ring_buffer.py
cace/common/safe_eval.py
cace/common/spiceunits.py
cace/gui/__init__.py
cace/gui/consoletext.py
cace/gui/editparam.py
cace/gui/failreport.py
cace/gui/helpwindow.py
cace/gui/rowwidget.py
cace/gui/settings.py
cace/gui/simhints.py
cace/gui/style.py
cace/gui/textreport.py
cace/gui/tksimpledialog.py
cace/gui/tooltip.py
cace/logging/__init__.py
cace/logging/logger.py
cace/parameter/__init__.py
cace/parameter/parameter.py
cace/parameter/parameter_klayout_drc.py
cace/parameter/parameter_klayout_lvs.py
cace/parameter/parameter_magic_antenna_check.py
cace/parameter/parameter_magic_area.py
cace/parameter/parameter_magic_drc.py
cace/parameter/parameter_manager.py
cace/parameter/parameter_netgen_lvs.py
cace/parameter/parameter_ngspice.py
cace-2.8.3.dist-info/AUTHORS.md
cace-2.8.3.dist-info/LICENSE
cace-2.8.3.dist-info/METADATA
cace-2.8.3.dist-info/WHEEL
cace-2.8.3.dist-info/entry_points.txt
cace-2.8.3.dist-info/top_level.txt
cace-2.8.3.dist-info/RECORD
