Metadata-Version: 2.1
Name: cace
Version: 2.8.3
Summary: Circuit Automatic Characterization Engine
Author-email: Tim Edwards <tim@opencircuitdesign.com>, Leo Moser <leo.moser@pm.me>
Project-URL: Homepage, https://github.com/fossi-foundation/cace
Project-URL: Issues, https://github.com/fossi-foundation/cace/issues
Classifier: Programming Language :: Python :: 3
Classifier: License :: OSI Approved :: Apache Software License
Classifier: Operating System :: OS Independent
Requires-Python: >=3.8
License-File: LICENSE
License-File: AUTHORS.md
Requires-Dist: matplotlib >=3.6.0
Requires-Dist: numpy >=1.20.0
Requires-Dist: pillow >=10.1.0
Requires-Dist: ciel >=0.16.0
Requires-Dist: rich <15,>=13
